<?xml version="1.0"?>
<wayfire>
	<plugin name="blur">
	<_short>Blur Windows</_short>
	<category>Effects</category>
	<option name="method" type="string">
		<_short>Blur Method</_short>
		<default>kawase</default>
		<desc>
			<value>box</value>
			<_name>Box</_name>
		</desc>
		<desc>
			<value>gaussian</value>
			<_name>Gaussian</_name>
		</desc>
		<desc>
			<value>kawase</value>
			<_name>Dual Kawase</_name>
		</desc>
		<desc>
			<value>bokeh</value>
			<_name>Bokeh</_name>
		</desc>
	</option>
	<option name="box_iterations" type="int">
		<_short>Box Iterations</_short>
		<default>2</default>
		<min>0</min>
		<max>25</max>
	</option>
	<option name="box_offset" type="double">
		<_short>Box Offset</_short>
		<default>2</default>
		<min>0</min>
		<max>25</max>
	</option>
	<option name="box_degrade" type="int">
		<_short>Box Degrade</_short>
		<default>1</default>
		<min>1</min>
		<max>5</max>
	</option>
	<option name="gaussian_iterations" type="int">
		<_short>Gaussian Iterations</_short>
		<default>2</default>
		<min>0</min>
		<max>25</max>
	</option>
	<option name="gaussian_offset" type="double">
		<_short>Gaussian Offset</_short>
		<default>2</default>
		<min>0</min>
		<max>25</max>
	</option>
	<option name="gaussian_degrade" type="int">
		<_short>Gaussian Degrade</_short>
		<default>1</default>
		<min>1</min>
		<max>5</max>
	</option>
	<option name="kawase_iterations" type="int">
		<_short>Kawase Iterations</_short>
		<default>2</default>
		<min>0</min>
		<max>10</max>
	</option>
	<option name="kawase_offset" type="double">
		<_short>Kawase Offset</_short>
		<default>5</default>
		<min>0</min>
		<max>25</max>
	</option>
	<option name="kawase_degrade" type="int">
		<_short>Kawase Degrade</_short>
		<default>1</default>
		<min>1</min>
		<max>5</max>
	</option>
	<option name="bokeh_iterations" type="int">
		<_short>Bokeh Iterations</_short>
		<default>15</default>
		<min>0</min>
		<max>250</max>
	</option>
	<option name="bokeh_offset" type="double">
		<_short>Bokeh Offset</_short>
		<default>5</default>
		<min>0</min>
		<max>50</max>
	</option>
	<option name="bokeh_degrade" type="int">
		<_short>Bokeh Degrade</_short>
		<default>1</default>
		<min>1</min>
		<max>5</max>
	</option>
	<option name="toggle" type="button">
		<_short>Toggle</_short>
		<default>&lt;super&gt; &lt;alt&gt; BTN_LEFT</default>
	</option>
	</plugin>
</wayfire>
